TCLIService/TCLIService.py
TCLIService/__init__.py
TCLIService/constants.py
TCLIService/ttypes.py
pyhive/__init__.py
pyhive/common.py
pyhive/exc.py
pyhive/hive.py
pyhive/presto.py
pyhive/sqlalchemy_hive.py
pyhive/sqlalchemy_presto.py
pyhive/sqlalchemy_trino.py
pyhive/trino.py
openmetadata_sqlalchemy_hive-0.2.0.dist-info/LICENSE
openmetadata_sqlalchemy_hive-0.2.0.dist-info/METADATA
openmetadata_sqlalchemy_hive-0.2.0.dist-info/WHEEL
openmetadata_sqlalchemy_hive-0.2.0.dist-info/entry_points.txt
openmetadata_sqlalchemy_hive-0.2.0.dist-info/top_level.txt
openmetadata_sqlalchemy_hive-0.2.0.dist-info/RECORD
