Metadata-Version: 2.1
Name: openmetadata-sqlalchemy-hive
Version: 0.2.0
Summary: Python interface to Hive for Openmetadata
Home-page: https://github.com/dropbox/PyHive
Author: Openmetadata Committers
License: Apache License, Version 2.0
Platform: UNKNOWN
Classifier: Intended Audience :: Developers
Classifier: License :: OSI Approved :: Apache Software License
Classifier: Operating System :: OS Independent
Classifier: Topic :: Database :: Front-Ends
License-File: LICENSE
Requires-Dist: future
Requires-Dist: python-dateutil
Provides-Extra: hive
Requires-Dist: sasl (>=0.2.1) ; extra == 'hive'
Requires-Dist: thrift (>=0.10.0) ; extra == 'hive'
Requires-Dist: thrift-sasl (>=0.1.0) ; extra == 'hive'
Provides-Extra: kerberos
Requires-Dist: requests-kerberos (>=0.12.0) ; extra == 'kerberos'
Provides-Extra: presto
Requires-Dist: requests (>=1.0.0) ; extra == 'presto'
Requires-Dist: presto-types-parser (>=0.0.2) ; extra == 'presto'
Provides-Extra: sqlalchemy
Requires-Dist: sqlalchemy (>=1.3.0) ; extra == 'sqlalchemy'
Provides-Extra: trino
Requires-Dist: requests (>=1.0.0) ; extra == 'trino'
Requires-Dist: presto-types-parser (>=0.0.2) ; extra == 'trino'
